pipiyiTools/EpubSpliter.py
pipiyiTools/FileOperation.py
pipiyiTools/ListQueue.py
pipiyiTools/Log.py
pipiyiTools/MyRequest.py
pipiyiTools/PooledBase.py
pipiyiTools/Storage.py
pipiyiTools/__init__.py
pipiyiTools-0.0.1.dist-info/METADATA
pipiyiTools-0.0.1.dist-info/WHEEL
pipiyiTools-0.0.1.dist-info/top_level.txt
pipiyiTools-0.0.1.dist-info/RECORD
