Metadata-Version: 2.1
Name: pipiyiTools
Version: 0.0.1
Summary: Personal tool library
Home-page: UNKNOWN
Author: pipiyi
Author-email: smallpoliao@gmail.com
License: UNKNOWN
Keywords: python
Platform: UNKNOWN
Classifier: Development Status :: 1 - Planning
Classifier: Intended Audience :: Developers
Classifier: Programming Language :: Python :: 3
Classifier: Operating System :: Unix
Classifier: Operating System :: MacOS :: MacOS X
Classifier: Operating System :: Microsoft :: Windows
Requires-Dist: requests
Requires-Dist: ebooklib
Requires-Dist: colorlog
Requires-Dist: dbutils
Requires-Dist: pymysql
